qgrabber/__init__.py
qgrabber/controller.py
qgrabber/model.py
qgrabber/view.py
qgrabber-0.0.8.dist-info/LICENSE
qgrabber-0.0.8.dist-info/WHEEL
qgrabber-0.0.8.dist-info/METADATA
qgrabber-0.0.8.dist-info/RECORD
