Metadata-Version: 2.1
Name: qgrabber
Version: 0.0.8
Summary: Scan QR codes using your webcam, pyzbar and wxpython. No usage of opencv
Home-page: https://github.com/sander76/qrabber
License: UNKNOWN
Author: Sander Teunissen
Author-email: no_mail@nomail.com
Requires-Python: >=3.7
Classifier: License :: OSI Approved :: MIT License
Requires-Dist: aio_wx_widgets
Requires-Dist: pyzbar
Requires-Dist: videocapture
Requires-Dist: pylint ; extra == "dev"
Requires-Dist: nox ; extra == "dev"
Requires-Dist: pytest-cov ; extra == "dev"
Requires-Dist: coverage[toml]>=5.0.3 ; extra == "dev"
Requires-Dist: pre-commit ; extra == "dev"
Requires-Dist: pytest ; extra == "test"
Requires-Dist: pytest-asyncio ; extra == "test"
Requires-Dist: pytest-mock ; extra == "test"
Provides-Extra: dev
Provides-Extra: test
